tests/__init__.py
tests/test_fibonacci.py
pystarlark-0.0.2.dist-info/LICENSE
pystarlark-0.0.2.dist-info/METADATA
pystarlark-0.0.2.dist-info/top_level.txt
pystarlark-0.0.2.dist-info/WHEEL
pystarlark-0.0.2.dist-info/RECORD
pystarlark/starlark.cpython-37m-x86_64-linux-gnu.h
pystarlark/__init__.py
pystarlark/starlark.cpython-37m-x86_64-linux-gnu.so
