Metadata-Version: 2.1
Name: pystarlark
Version: 0.0.2
Summary: Python bindings for Starlark in Go
Home-page: https://github.com/ColdHeat/pystarlark
Author: Kevin Chung
Author-email: kchung@nyu.edu
License: UNKNOWN
Platform: UNKNOWN
Classifier: Programming Language :: Python :: 3
Classifier: License :: OSI Approved :: MIT License
Classifier: Operating System :: OS Independent
Requires-Python: >=3.6
